{
  "id": "mnoaroa5",
  "display_name": "Min. Obs. Apnea length w/ arousals (REM, Other, 5% desat)",
  "description": "Min. Obs. Apnea length w/ arousals (REM, Other, 5% desat) (seconds)",
  "type": "numeric",
  "units": "second",
  "labels": [
    "mnoaroa5"
  ],
  "hybrid": {
    "VARNUM": "220",
    "TABLE": "SHHS2",
    "LABEL": "Min. Obs. Apnea length w/ arousals (REM, Other, 5% desat) (seconds)",
    "access level": "0",
    "SOURCE": "PSG Report (SHHS2)",
    "MEMNAME": "shhs2_2",
    "most commonly used": null,
    "filename": null,
    "PARENT TERM": null
  }
}
