{
  "id": "oanba2",
  "display_name": "Number of Obstructive Apnea w/ arousals (NREM, Back, 2% oxygen desaturation)",
  "description": "Number of Obstructive Apnea w/ arousals (NREM, Back, 2% oxygen desaturation)",
  "type": "numeric",
  "units": "obstructive apnea events",
  "labels": [
    "oanba2"
  ],
  "hybrid": {
    "VARNUM": "570",
    "TABLE": "SHHS2",
    "LABEL": "Number of Obstructive Apnea w/ arousals (NREM, Back, 2% oxygen desaturation)",
    "sensitivity": "0",
    "design_name": "PSG Report (SHHS2)",
    "MEMNAME": "shhs2_1",
    "design_file": null,
    "PARENT TERM": "psg:oa"
  }
}
