{
  "id": "hnroa",
  "display_name": "# of Hypopnea w/ arousals (NREM, Other, all desats)",
  "description": "# of Hypopnea w/ arousals (NREM, Other, all desats)",
  "type": "numeric",
  "units": "event count",
  "labels": [
    "hnroa"
  ],
  "hybrid": {
    "VARNUM": "422",
    "TABLE": "SHHS2",
    "LABEL": "# of Hypopnea w/ arousals (NREM, Other, all desats)",
    "access level": "0",
    "design_name": "PSG Report (SHHS2)",
    "MEMNAME": "shhs2_1",
    "most commonly used": null,
    "design_file": null,
    "PARENT TERM": "psg:hypopnea"
  }
}
