{
  "id": "rcvddtqa",
  "display_name": "PSG Quality Assessment (SHHS1): Date Received at RC",
  "description": "",
  "type": "numeric",
  "units": "days from index date",
  "labels": [
    "RcvdDtqa",
    "Polysomnography"
  ],
  "forms": [
    "shhs1_sleep_data_quality_assessment_and_preliminary_report_form"
  ],
  "hybrid": {
    "VARNUM": "585",
    "TABLE": "SHHS1",
    "LABEL": "Date Received at RC",
    "sensitivity": "0",
    "design_name": "PSG Quality Assessment (SHHS1)",
    "MEMNAME": "shhs1_2",
    "design_file": "SHHS1 PSG Quality Assessment (QC).pdf",
    "PARENT TERM": null
  }
}
