{
  "id": "canbp5",
  "display_name": "Number of Central Apnea (NREM, Back, 5% oxygen desaturation)",
  "description": "Number of Central Apnea (NREM, Back, 5% oxygen desaturation)",
  "type": "numeric",
  "units": "central apnea events",
  "labels": [
    "canbp5"
  ],
  "hybrid": {
    "VARNUM": "146",
    "TABLE": "SHHS2",
    "LABEL": "Number of Central Apnea (NREM, Back, 5% oxygen desaturation)",
    "sensitivity": "0",
    "design_name": "PSG Report (SHHS2)",
    "MEMNAME": "shhs2_2",
    "design_file": null,
    "PARENT TERM": "psg:ca"
  }
}
