{
  "id": "cardroa2",
  "display_name": "Central Apnea per hour w/ arousals (REM, Other, 2% oxygen desaturation)",
  "description": "Central Apnea per hour w/ arousals (REM, Other, 2% oxygen desaturation)",
  "type": "numeric",
  "units": "events per hour",
  "labels": [
    "cardroa2",
    "Sleep Apnea, Central",
    "Arousal"
  ],
  "hybrid": {
    "VARNUM": "369",
    "TABLE": "SHHS2",
    "LABEL": "Central Apnea per hour w/ arousals (REM, Other, 2% oxygen desaturation)",
    "sensitivity": "0",
    "design_name": "PSG Report (SHHS2)",
    "MEMNAME": "shhs2_2",
    "design_file": null,
    "PARENT TERM": "psg:cai"
  }
}
