{
  "id": "hrop5",
  "display_name": "# of Hypopnea (REM, Other, 5% desat) (SHHS2)",
  "description": "# of Hypopnea (REM, Other, 5% desat)",
  "type": "numeric",
  "units": "event_count",
  "labels": [
    "hrop5"
  ],
  "hybrid": {
    "VARNUM": "126",
    "TABLE": "SHHS2",
    "LABEL": "# of Hypopnea (REM, Other, 5% desat)",
    "access level": "0",
    "SOURCE": "PSG Report (SHHS2)",
    "MEMNAME": "shhs2_2",
    "most commonly used": null,
    "filename": null,
    "PARENT TERM": "psg:hypopnea"
  }
}
