{
  "id": "ql203a",
  "display_name": "Quality of Life (QOL) (Sleep Heart Health Study Visit Two (SHHS2)): Health limits vigorous activities",
  "description": "3. The following questions are about activities you might do during a typical day. Does your health now limit you in these activities? If so, how much? (Check one box for each question.) a. Vigorous activities, such as running, lifting heavy objects, participating in strenuous sports.",
  "type": "choices",
  "domain": "lotlitn",
  "forms": [
    "shhs2_quality_of_life_sf_36_form"
  ]
}
