{
  "id": "hrqual",
  "display_name": "PSG Quality Assessment (SHHS1): Signal Quality (hr)",
  "description": "Overall quality of signal from heart rate (ECG) leads as assessed by scorer.",
  "type": "choices",
  "domain": "sigqus1",
  "labels": [
    "HRqual"
  ],
  "forms": [
    "shhs1_sleep_data_quality_assessment_and_preliminary_report_form"
  ],
  "hybrid": {
    "VARNUM": "601",
    "TABLE": "SHHS1",
    "LABEL": "HRqual",
    "sensitivity": "0",
    "design_name": "PSG Quality Assessment (SHHS1)",
    "MEMNAME": "shhs1_2",
    "design_file": "SHHS1 PSG Quality Assessment (QC).pdf",
    "PARENT TERM": null
  }
}
