{
  "id": "mxdroa",
  "display_name": "Max. Desat w/ arousals (REM, Other, all desats)",
  "description": "Max. Desat w/ arousals (REM, Other, all desats)",
  "type": "numeric",
  "units": "percent",
  "labels": [
    "mxdroa"
  ],
  "hybrid": {
    "VARNUM": "459",
    "TABLE": "SHHS2",
    "LABEL": "Max. Desat w/ arousals (REM, Other, all desats)",
    "access level": "0",
    "design_name": "PSG Report (SHHS2)",
    "MEMNAME": "shhs2_1",
    "most commonly used": null,
    "design_file": null,
    "PARENT TERM": null
  }
}
