{
  "id": "mxdrop2",
  "display_name": "Max. oxygen desaturation (REM, Other, 2% oxygen desaturation)",
  "description": "Max. oxygen desaturation (REM, Other, 2% oxygen desaturation)",
  "type": "numeric",
  "units": "percent",
  "labels": [
    "mxdrop2"
  ],
  "hybrid": {
    "VARNUM": "519",
    "TABLE": "SHHS2",
    "LABEL": "Max. oxygen desaturation (REM, Other, 2% oxygen desaturation)",
    "sensitivity": "0",
    "design_name": "PSG Report (SHHS2)",
    "MEMNAME": "shhs2_1",
    "design_file": null,
    "PARENT TERM": null
  }
}
