{
  "id": "sh313",
  "display_name": "Sleep Habits (SHHS2): Surgery for snoring",
  "description": "To answer these questions, please consider both what others have told you AND what you know about yourself.  13. Have you ever had somnoplasty, laser treatment, or surgery as treatment for your snoring?",
  "type": "choices",
  "domain": "yesno01",
  "labels": [
    "sh313"
  ],
  "hybrid": {
    "VARNUM": "26",
    "TABLE": "SHHS2",
    "LABEL": "SH 13  Ever had somnoplasty/surgery for sno",
    "sensitivity": "0",
    "design_name": "Sleep Habits (SHHS2)",
    "MEMNAME": "shhs2_1",
    "design_file": "SHHS2 Sleep Habits (SH).pdf",
    "PARENT TERM": null
  }
}
