{
  "id": "davbnbh",
  "display_name": "Avg. Heart Rate with arousal (NREM, Back, 3% desat)",
  "description": "",
  "type": "numeric",
  "units": "beats per minute",
  "labels": [
    "davbnbh"
  ],
  "hybrid": {
    "VARNUM": "284",
    "TABLE": "SHHS2",
    "LABEL": "Avg. Heart Rate with arousal (NREM, Back, 3% desat) (bpm)",
    "access level": "0",
    "design_name": "PSG Report (SHHS2)",
    "MEMNAME": "shhs2_2",
    "most commonly used": null,
    "design_file": null,
    "PARENT TERM": "psg:avgheartrate"
  }
}
